topsis/__init__.py
topsis/topsis.py
Topsis_Madhav_102203782-1.0.2.dist-info/LICENSE
Topsis_Madhav_102203782-1.0.2.dist-info/METADATA
Topsis_Madhav_102203782-1.0.2.dist-info/WHEEL
Topsis_Madhav_102203782-1.0.2.dist-info/entry_points.txt
Topsis_Madhav_102203782-1.0.2.dist-info/top_level.txt
Topsis_Madhav_102203782-1.0.2.dist-info/RECORD
