Metadata-Version: 2.1
Name: Topsis-Madhav-102203782
Version: 1.0.2
Summary: A Python package to perform TOPSIS (Technique for Order Preference by Similarity to Ideal Solution)
Author: Madhav Garg
Author-email: gargmadhav90@gmail.com
Classifier: Programming Language :: Python :: 3
Classifier: License :: OSI Approved :: MIT License
Classifier: Operating System :: OS Independent
Requires-Python: >=3.6
License-File: LICENSE
Requires-Dist: numpy
Requires-Dist: pandas
